markup_front_matter_parser/__init__.py
markup_front_matter_parser/file_format.py
markup_front_matter_parser/front_matter_parser_factory.py
markup_front_matter_parser/invalid_front_matter_error.py
markup_front_matter_parser/models/markup_content.py
markup_front_matter_parser/models/markup_file.py
markup_front_matter_parser/parsers/abstract_front_matter_parser.py
markup_front_matter_parser/parsers/html_front_matter_parser.py
markup_front_matter_parser/parsers/markdown_front_matter_parser.py
markup_front_matter_parser-0.6.0.dist-info/licenses/LICENSE
markup_front_matter_parser-0.6.0.dist-info/METADATA
markup_front_matter_parser-0.6.0.dist-info/WHEEL
markup_front_matter_parser-0.6.0.dist-info/top_level.txt
markup_front_matter_parser-0.6.0.dist-info/RECORD
