Metadata-Version: 2.4
Name: markup-front-matter-parser
Version: 0.6.0
Summary: An OOP-y front matter parser for markup files
Author-email: Jamison Griffith <jamison.griffith@gmail.com>
License-Expression: MIT
Project-URL: Homepage, https://github.com/jamogriff/markup-front-matter-parser
Project-URL: Documentation, https://github.com/jamogriff/markup-front-matter-parser/blob/main/README.md
Project-URL: Source, https://github.com/jamogriff/markup-front-matter-parser
Project-URL: Issues, https://github.com/jamogriff/markup-front-matter-parser/issues
Keywords: markup,front matter,parser,markdown,html,jekyll,development,factory pattern
Classifier: Intended Audience :: Developers
Classifier: Development Status :: 4 - Beta
Classifier: Operating System :: OS Independent
Classifier: Programming Language :: Python :: 3.10
Classifier: Programming Language :: Python :: 3.15
Classifier: Topic :: File Formats
Classifier: Topic :: Software Development
Classifier: Topic :: Software Development :: Libraries :: Python Modules
Classifier: Topic :: Text Processing :: Markup
Classifier: Topic :: Text Processing :: Markup :: HTML
Classifier: Topic :: Text Processing :: Markup :: Markdown
Requires-Python: >=3.10
License-File: LICENSE
Provides-Extra: code-style
Requires-Dist: black; extra == "code-style"
Provides-Extra: testing
Requires-Dist: pytest; extra == "testing"
Provides-Extra: typing
Requires-Dist: mypy; extra == "typing"
Dynamic: license-file
